[
  {
    "creator_id": "c-001",
    "handle": "@laurelandsage",
    "tier": "elite",
    "currency": "USD",
    "orders_counted": 11,
    "orders_excluded": 2,
    "gross_revenue": 2300.52,
    "total_refunds": 190.51,
    "total_shipping": 70.14,
    "total_platform_fees": 46,
    "total_promo_credits": 19.54,
    "commissionable_base": 1993.87,
    "commission_rate": 0.14,
    "gross_commission": 279.14,
    "net_payout_native": 279.14,
    "net_payout_usd": 279.14,
    "meets_minimum_threshold": true,
    "payout_status": "paid_out"
  },
  {
    "creator_id": "c-002",
    "handle": "@morningbarrow",
    "tier": "plus",
    "currency": "USD",
    "orders_counted": 25,
    "orders_excluded": 4,
    "gross_revenue": 6019.28,
    "total_refunds": 299.38,
    "total_shipping": 156.95,
    "total_platform_fees": 120.38,
    "total_promo_credits": 139.75,
    "commissionable_base": 5302.82,
    "commission_rate": 0.11,
    "gross_commission": 583.31,
    "net_payout_native": 583.31,
    "net_payout_usd": 583.31,
    "meets_minimum_threshold": true,
    "payout_status": "paid_out"
  },
  {
    "creator_id": "c-003",
    "handle": "@runnerstype",
    "tier": "standard",
    "currency": "USD",
    "orders_counted": 16,
    "orders_excluded": 1,
    "gross_revenue": 3626.98,
    "total_refunds": 122.2,
    "total_shipping": 93.6,
    "total_platform_fees": 72.55,
    "total_promo_credits": 14.26,
    "commissionable_base": 3324.37,
    "commission_rate": 0.08,
    "gross_commission": 265.95,
    "net_payout_native": 265.95,
    "net_payout_usd": 265.95,
    "meets_minimum_threshold": true,
    "payout_status": "paid_out"
  },
  {
    "creator_id": "c-004",
    "handle": "@theatticedits",
    "tier": "plus",
    "currency": "EUR",
    "orders_counted": 26,
    "orders_excluded": 2,
    "gross_revenue": 5655.85,
    "total_refunds": 320.97,
    "total_shipping": 185.11,
    "total_platform_fees": 113.14,
    "total_promo_credits": 121.57,
    "commissionable_base": 4915.06,
    "commission_rate": 0.11,
    "gross_commission": 540.66,
    "net_payout_native": 540.66,
    "net_payout_usd": 589.32,
    "meets_minimum_threshold": true,
    "payout_status": "paid_out"
  },
  {
    "creator_id": "c-005",
    "handle": "@batchnotbought",
    "tier": "standard",
    "currency": "USD",
    "orders_counted": 22,
    "orders_excluded": 2,
    "gross_revenue": 4871.55,
    "total_refunds": 91.98,
    "total_shipping": 165.75,
    "total_platform_fees": 97.45,
    "total_promo_credits": 58.1,
    "commissionable_base": 4458.27,
    "commission_rate": 0.08,
    "gross_commission": 356.66,
    "net_payout_native": 356.66,
    "net_payout_usd": 356.66,
    "meets_minimum_threshold": true,
    "payout_status": "paid_out"
  },
  {
    "creator_id": "c-006",
    "handle": "@chiplabsbeauty",
    "tier": "elite",
    "currency": "GBP",
    "orders_counted": 8,
    "orders_excluded": 0,
    "gross_revenue": 2034.1,
    "total_refunds": 0,
    "total_shipping": 68.69,
    "total_platform_fees": 40.68,
    "total_promo_credits": 40.6,
    "commissionable_base": 1924.73,
    "commission_rate": 0.14,
    "gross_commission": 269.46,
    "net_payout_native": 269.46,
    "net_payout_usd": 344.91,
    "meets_minimum_threshold": true,
    "payout_status": "paid_out"
  },
  {
    "creator_id": "c-007",
    "handle": "@kindredkit",
    "tier": "plus",
    "currency": "USD",
    "orders_counted": 16,
    "orders_excluded": 0,
    "gross_revenue": 3225.55,
    "total_refunds": 0,
    "total_shipping": 96.21,
    "total_platform_fees": 64.52,
    "total_promo_credits": 36.24,
    "commissionable_base": 3028.58,
    "commission_rate": 0.11,
    "gross_commission": 333.14,
    "net_payout_native": 333.14,
    "net_payout_usd": 333.14,
    "meets_minimum_threshold": true,
    "payout_status": "paid_out"
  },
  {
    "creator_id": "c-008",
    "handle": "@protocolfit",
    "tier": "standard",
    "currency": "CAD",
    "orders_counted": 20,
    "orders_excluded": 0,
    "gross_revenue": 3723.76,
    "total_refunds": 0,
    "total_shipping": 150.29,
    "total_platform_fees": 74.5,
    "total_promo_credits": 93.94,
    "commissionable_base": 3405.03,
    "commission_rate": 0.08,
    "gross_commission": 272.4,
    "net_payout_native": 272.4,
    "net_payout_usd": 201.58,
    "meets_minimum_threshold": true,
    "payout_status": "paid_out"
  },
  {
    "creator_id": "c-009",
    "handle": "@oakfacedstudio",
    "tier": "plus",
    "currency": "USD",
    "orders_counted": 18,
    "orders_excluded": 2,
    "gross_revenue": 3458.5,
    "total_refunds": 334.55,
    "total_shipping": 109.41,
    "total_platform_fees": 69.17,
    "total_promo_credits": 91.52,
    "commissionable_base": 2853.85,
    "commission_rate": 0.11,
    "gross_commission": 313.92,
    "net_payout_native": 313.92,
    "net_payout_usd": 313.92,
    "meets_minimum_threshold": true,
    "payout_status": "paid_out"
  },
  {
    "creator_id": "c-010",
    "handle": "@northfacelab",
    "tier": "elite",
    "currency": "USD",
    "orders_counted": 26,
    "orders_excluded": 1,
    "gross_revenue": 5015.29,
    "total_refunds": 61.44,
    "total_shipping": 159.14,
    "total_platform_fees": 100.32,
    "total_promo_credits": 15.57,
    "commissionable_base": 4694.39,
    "commission_rate": 0.14,
    "gross_commission": 657.21,
    "net_payout_native": 657.21,
    "net_payout_usd": 657.21,
    "meets_minimum_threshold": true,
    "payout_status": "paid_out"
  },
  {
    "creator_id": "c-011",
    "handle": "@quietmonth",
    "tier": "standard",
    "currency": "EUR",
    "orders_counted": 16,
    "orders_excluded": 4,
    "gross_revenue": 3585.44,
    "total_refunds": 687.32,
    "total_shipping": 105.91,
    "total_platform_fees": 71.7,
    "total_promo_credits": 98.79,
    "commissionable_base": 2621.72,
    "commission_rate": 0.08,
    "gross_commission": 209.74,
    "net_payout_native": 209.74,
    "net_payout_usd": 228.61,
    "meets_minimum_threshold": true,
    "payout_status": "paid_out"
  },
  {
    "creator_id": "c-012",
    "handle": "@wandercoded",
    "tier": "plus",
    "currency": "USD",
    "orders_counted": 12,
    "orders_excluded": 0,
    "gross_revenue": 2544.46,
    "total_refunds": 132.04,
    "total_shipping": 64.52,
    "total_platform_fees": 50.89,
    "total_promo_credits": 25.39,
    "commissionable_base": 2271.62,
    "commission_rate": 0.11,
    "gross_commission": 249.88,
    "net_payout_native": 249.88,
    "net_payout_usd": 249.88,
    "meets_minimum_threshold": true,
    "payout_status": "paid_out"
  },
  {
    "creator_id": "c-013",
    "handle": "@halflightcollection",
    "tier": "standard",
    "currency": "USD",
    "orders_counted": 21,
    "orders_excluded": 1,
    "gross_revenue": 3738.38,
    "total_refunds": 0,
    "total_shipping": 128.31,
    "total_platform_fees": 74.77,
    "total_promo_credits": 29.91,
    "commissionable_base": 3505.39,
    "commission_rate": 0.08,
    "gross_commission": 280.43,
    "net_payout_native": 280.43,
    "net_payout_usd": 280.43,
    "meets_minimum_threshold": true,
    "payout_status": "paid_out"
  },
  {
    "creator_id": "c-014",
    "handle": "@everydaybatch",
    "tier": "standard",
    "currency": "USD",
    "orders_counted": 15,
    "orders_excluded": 1,
    "gross_revenue": 3111.76,
    "total_refunds": 123.32,
    "total_shipping": 82.74,
    "total_platform_fees": 62.22,
    "total_promo_credits": 58.76,
    "commissionable_base": 2784.72,
    "commission_rate": 0.08,
    "gross_commission": 222.78,
    "net_payout_native": 222.78,
    "net_payout_usd": 222.78,
    "meets_minimum_threshold": true,
    "payout_status": "paid_out"
  },
  {
    "creator_id": "c-015",
    "handle": "@cedarmeasure",
    "tier": "plus",
    "currency": "CAD",
    "orders_counted": 14,
    "orders_excluded": 0,
    "gross_revenue": 3055.57,
    "total_refunds": 0,
    "total_shipping": 96.66,
    "total_platform_fees": 61.12,
    "total_promo_credits": 37.87,
    "commissionable_base": 2859.92,
    "commission_rate": 0.11,
    "gross_commission": 314.59,
    "net_payout_native": 314.59,
    "net_payout_usd": 232.8,
    "meets_minimum_threshold": true,
    "payout_status": "paid_out"
  },
  {
    "creator_id": "c-016",
    "handle": "@nightowltype",
    "tier": "standard",
    "currency": "USD",
    "orders_counted": 7,
    "orders_excluded": 1,
    "gross_revenue": 913.99,
    "total_refunds": 0,
    "total_shipping": 49.72,
    "total_platform_fees": 18.28,
    "total_promo_credits": 3.37,
    "commissionable_base": 842.62,
    "commission_rate": 0.08,
    "gross_commission": 67.41,
    "net_payout_native": 67.41,
    "net_payout_usd": 67.41,
    "meets_minimum_threshold": true,
    "payout_status": "paid_out"
  },
  {
    "creator_id": "c-017",
    "handle": "@parlourgrade",
    "tier": "elite",
    "currency": "USD",
    "orders_counted": 8,
    "orders_excluded": 1,
    "gross_revenue": 1506,
    "total_refunds": 132.74,
    "total_shipping": 59.03,
    "total_platform_fees": 30.11,
    "total_promo_credits": 18.76,
    "commissionable_base": 1284.12,
    "commission_rate": 0.14,
    "gross_commission": 179.78,
    "net_payout_native": 179.78,
    "net_payout_usd": 179.78,
    "meets_minimum_threshold": true,
    "payout_status": "paid_out"
  },
  {
    "creator_id": "c-018",
    "handle": "@flatlandstyle",
    "tier": "plus",
    "currency": "USD",
    "orders_counted": 9,
    "orders_excluded": 0,
    "gross_revenue": 2342.32,
    "total_refunds": 0,
    "total_shipping": 41.15,
    "total_platform_fees": 46.86,
    "total_promo_credits": 89.38,
    "commissionable_base": 2164.93,
    "commission_rate": 0.11,
    "gross_commission": 238.14,
    "net_payout_native": 238.14,
    "net_payout_usd": 238.14,
    "meets_minimum_threshold": true,
    "payout_status": "paid_out"
  },
  {
    "creator_id": "c-019",
    "handle": "@formandfilament",
    "tier": "standard",
    "currency": "EUR",
    "orders_counted": 13,
    "orders_excluded": 1,
    "gross_revenue": 3540.15,
    "total_refunds": 363.1,
    "total_shipping": 77.54,
    "total_platform_fees": 70.8,
    "total_promo_credits": 138.77,
    "commissionable_base": 2889.94,
    "commission_rate": 0.08,
    "gross_commission": 231.2,
    "net_payout_native": 231.2,
    "net_payout_usd": 252,
    "meets_minimum_threshold": true,
    "payout_status": "paid_out"
  },
  {
    "creator_id": "c-020",
    "handle": "@deependsupply",
    "tier": "plus",
    "currency": "USD",
    "orders_counted": 8,
    "orders_excluded": 0,
    "gross_revenue": 1768.04,
    "total_refunds": 0,
    "total_shipping": 54.22,
    "total_platform_fees": 35.37,
    "total_promo_credits": 56.4,
    "commissionable_base": 1622.05,
    "commission_rate": 0.11,
    "gross_commission": 178.43,
    "net_payout_native": 178.43,
    "net_payout_usd": 178.43,
    "meets_minimum_threshold": true,
    "payout_status": "paid_out"
  },
  {
    "creator_id": "c-021",
    "handle": "@homemakeover.diy",
    "tier": "standard",
    "currency": "USD",
    "orders_counted": 25,
    "orders_excluded": 2,
    "gross_revenue": 5652.43,
    "total_refunds": 367.76,
    "total_shipping": 162.87,
    "total_platform_fees": 113.07,
    "total_promo_credits": 119.04,
    "commissionable_base": 4889.69,
    "commission_rate": 0.08,
    "gross_commission": 391.18,
    "net_payout_native": 391.18,
    "net_payout_usd": 391.18,
    "meets_minimum_threshold": true,
    "payout_status": "paid_out"
  },
  {
    "creator_id": "c-022",
    "handle": "@brightnotebook",
    "tier": "plus",
    "currency": "GBP",
    "orders_counted": 15,
    "orders_excluded": 1,
    "gross_revenue": 3233.45,
    "total_refunds": 0,
    "total_shipping": 62.91,
    "total_platform_fees": 64.69,
    "total_promo_credits": 130.36,
    "commissionable_base": 2975.49,
    "commission_rate": 0.11,
    "gross_commission": 327.3,
    "net_payout_native": 327.3,
    "net_payout_usd": 418.95,
    "meets_minimum_threshold": true,
    "payout_status": "paid_out"
  },
  {
    "creator_id": "c-023",
    "handle": "@longshelfstaples",
    "tier": "standard",
    "currency": "USD",
    "orders_counted": 13,
    "orders_excluded": 0,
    "gross_revenue": 2733.44,
    "total_refunds": 247.37,
    "total_shipping": 88.17,
    "total_platform_fees": 54.66,
    "total_promo_credits": 18.31,
    "commissionable_base": 2324.93,
    "commission_rate": 0.08,
    "gross_commission": 185.99,
    "net_payout_native": 185.99,
    "net_payout_usd": 185.99,
    "meets_minimum_threshold": true,
    "payout_status": "paid_out"
  },
  {
    "creator_id": "c-024",
    "handle": "@formulanorth",
    "tier": "elite",
    "currency": "CAD",
    "orders_counted": 23,
    "orders_excluded": 2,
    "gross_revenue": 5072.73,
    "total_refunds": 0,
    "total_shipping": 157.14,
    "total_platform_fees": 101.46,
    "total_promo_credits": 25.33,
    "commissionable_base": 4814.13,
    "commission_rate": 0.14,
    "gross_commission": 673.98,
    "net_payout_native": 673.98,
    "net_payout_usd": 498.74,
    "meets_minimum_threshold": true,
    "payout_status": "paid_out"
  },
  {
    "creator_id": "c-025",
    "handle": "@kitthesound",
    "tier": "plus",
    "currency": "USD",
    "orders_counted": 14,
    "orders_excluded": 1,
    "gross_revenue": 2745.58,
    "total_refunds": 717.15,
    "total_shipping": 70.82,
    "total_platform_fees": 54.92,
    "total_promo_credits": 76.14,
    "commissionable_base": 1826.55,
    "commission_rate": 0.11,
    "gross_commission": 200.92,
    "net_payout_native": 200.92,
    "net_payout_usd": 200.92,
    "meets_minimum_threshold": true,
    "payout_status": "paid_out"
  },
  {
    "creator_id": "c-026",
    "handle": "@dailyrepetition",
    "tier": "standard",
    "currency": "USD",
    "orders_counted": 13,
    "orders_excluded": 3,
    "gross_revenue": 2128.58,
    "total_refunds": 185.88,
    "total_shipping": 77.05,
    "total_platform_fees": 42.57,
    "total_promo_credits": 0,
    "commissionable_base": 1823.08,
    "commission_rate": 0.08,
    "gross_commission": 145.85,
    "net_payout_native": 145.85,
    "net_payout_usd": 145.85,
    "meets_minimum_threshold": true,
    "payout_status": "paid_out"
  },
  {
    "creator_id": "c-027",
    "handle": "@littleroomfinds",
    "tier": "plus",
    "currency": "USD",
    "orders_counted": 14,
    "orders_excluded": 1,
    "gross_revenue": 2291.21,
    "total_refunds": 0,
    "total_shipping": 98.17,
    "total_platform_fees": 45.82,
    "total_promo_credits": 25.3,
    "commissionable_base": 2121.92,
    "commission_rate": 0.11,
    "gross_commission": 233.41,
    "net_payout_native": 233.41,
    "net_payout_usd": 233.41,
    "meets_minimum_threshold": true,
    "payout_status": "paid_out"
  },
  {
    "creator_id": "c-028",
    "handle": "@porchlight.market",
    "tier": "standard",
    "currency": "USD",
    "orders_counted": 24,
    "orders_excluded": 4,
    "gross_revenue": 5378.87,
    "total_refunds": 219.61,
    "total_shipping": 172.29,
    "total_platform_fees": 107.58,
    "total_promo_credits": 121.73,
    "commissionable_base": 4757.66,
    "commission_rate": 0.08,
    "gross_commission": 380.61,
    "net_payout_native": 380.61,
    "net_payout_usd": 380.61,
    "meets_minimum_threshold": true,
    "payout_status": "paid_out"
  },
  {
    "creator_id": "c-029",
    "handle": "@firstprinciples.fit",
    "tier": "plus",
    "currency": "EUR",
    "orders_counted": 28,
    "orders_excluded": 3,
    "gross_revenue": 5346.48,
    "total_refunds": 465.35,
    "total_shipping": 126.48,
    "total_platform_fees": 106.93,
    "total_promo_credits": 73.54,
    "commissionable_base": 4574.18,
    "commission_rate": 0.11,
    "gross_commission": 503.16,
    "net_payout_native": 503.16,
    "net_payout_usd": 548.44,
    "meets_minimum_threshold": true,
    "payout_status": "paid_out"
  },
  {
    "creator_id": "c-030",
    "handle": "@onthewall.studio",
    "tier": "standard",
    "currency": "USD",
    "orders_counted": 9,
    "orders_excluded": 2,
    "gross_revenue": 2445.92,
    "total_refunds": 0,
    "total_shipping": 42.45,
    "total_platform_fees": 48.91,
    "total_promo_credits": 16.29,
    "commissionable_base": 2338.27,
    "commission_rate": 0.08,
    "gross_commission": 187.06,
    "net_payout_native": 187.06,
    "net_payout_usd": 187.06,
    "meets_minimum_threshold": true,
    "payout_status": "paid_out"
  },
  {
    "creator_id": "c-031",
    "handle": "@laundryandlight",
    "tier": "plus",
    "currency": "USD",
    "orders_counted": 20,
    "orders_excluded": 1,
    "gross_revenue": 4588.53,
    "total_refunds": 0,
    "total_shipping": 108.02,
    "total_platform_fees": 91.78,
    "total_promo_credits": 136.34,
    "commissionable_base": 4252.39,
    "commission_rate": 0.11,
    "gross_commission": 467.76,
    "net_payout_native": 467.76,
    "net_payout_usd": 467.76,
    "meets_minimum_threshold": true,
    "payout_status": "paid_out"
  },
  {
    "creator_id": "c-032",
    "handle": "@archivedfit",
    "tier": "standard",
    "currency": "GBP",
    "orders_counted": 11,
    "orders_excluded": 3,
    "gross_revenue": 2773.28,
    "total_refunds": 0,
    "total_shipping": 78.54,
    "total_platform_fees": 55.45,
    "total_promo_credits": 67.1,
    "commissionable_base": 2572.19,
    "commission_rate": 0.08,
    "gross_commission": 205.78,
    "net_payout_native": 205.78,
    "net_payout_usd": 263.39,
    "meets_minimum_threshold": true,
    "payout_status": "paid_out"
  },
  {
    "creator_id": "c-033",
    "handle": "@curatingdaily",
    "tier": "elite",
    "currency": "USD",
    "orders_counted": 16,
    "orders_excluded": 0,
    "gross_revenue": 3914.7,
    "total_refunds": 192.28,
    "total_shipping": 78.43,
    "total_platform_fees": 78.28,
    "total_promo_credits": 49.92,
    "commissionable_base": 3565.71,
    "commission_rate": 0.14,
    "gross_commission": 499.2,
    "net_payout_native": 499.2,
    "net_payout_usd": 499.2,
    "meets_minimum_threshold": true,
    "payout_status": "paid_out"
  },
  {
    "creator_id": "c-034",
    "handle": "@northcoastpantry",
    "tier": "plus",
    "currency": "CAD",
    "orders_counted": 10,
    "orders_excluded": 1,
    "gross_revenue": 2416.83,
    "total_refunds": 0,
    "total_shipping": 65.05,
    "total_platform_fees": 48.35,
    "total_promo_credits": 36.49,
    "commissionable_base": 2266.94,
    "commission_rate": 0.11,
    "gross_commission": 249.36,
    "net_payout_native": 249.36,
    "net_payout_usd": 184.53,
    "meets_minimum_threshold": true,
    "payout_status": "paid_out"
  },
  {
    "creator_id": "c-035",
    "handle": "@theslowlist",
    "tier": "standard",
    "currency": "USD",
    "orders_counted": 11,
    "orders_excluded": 1,
    "gross_revenue": 2535.36,
    "total_refunds": 0,
    "total_shipping": 68.94,
    "total_platform_fees": 50.72,
    "total_promo_credits": 52.42,
    "commissionable_base": 2363.28,
    "commission_rate": 0.08,
    "gross_commission": 189.06,
    "net_payout_native": 189.06,
    "net_payout_usd": 189.06,
    "meets_minimum_threshold": true,
    "payout_status": "paid_out"
  },
  {
    "creator_id": "c-036",
    "handle": "@workinggreen",
    "tier": "plus",
    "currency": "USD",
    "orders_counted": 13,
    "orders_excluded": 0,
    "gross_revenue": 3053.79,
    "total_refunds": 89.1,
    "total_shipping": 93.72,
    "total_platform_fees": 61.07,
    "total_promo_credits": 8.43,
    "commissionable_base": 2801.47,
    "commission_rate": 0.11,
    "gross_commission": 308.16,
    "net_payout_native": 308.16,
    "net_payout_usd": 308.16,
    "meets_minimum_threshold": true,
    "payout_status": "paid_out"
  },
  {
    "creator_id": "c-037",
    "handle": "@kelpfarm.creative",
    "tier": "standard",
    "currency": "USD",
    "orders_counted": 19,
    "orders_excluded": 3,
    "gross_revenue": 4385.6,
    "total_refunds": 0,
    "total_shipping": 97.93,
    "total_platform_fees": 87.7,
    "total_promo_credits": 64.19,
    "commissionable_base": 4135.78,
    "commission_rate": 0.08,
    "gross_commission": 330.86,
    "net_payout_native": 330.86,
    "net_payout_usd": 330.86,
    "meets_minimum_threshold": true,
    "payout_status": "paid_out"
  },
  {
    "creator_id": "c-038",
    "handle": "@theglassdesk",
    "tier": "plus",
    "currency": "USD",
    "orders_counted": 12,
    "orders_excluded": 1,
    "gross_revenue": 2805.26,
    "total_refunds": 0,
    "total_shipping": 93.46,
    "total_platform_fees": 56.11,
    "total_promo_credits": 66.27,
    "commissionable_base": 2589.42,
    "commission_rate": 0.11,
    "gross_commission": 284.84,
    "net_payout_native": 284.84,
    "net_payout_usd": 284.84,
    "meets_minimum_threshold": true,
    "payout_status": "paid_out"
  },
  {
    "creator_id": "c-039",
    "handle": "@longerlight.studio",
    "tier": "standard",
    "currency": "USD",
    "orders_counted": 23,
    "orders_excluded": 2,
    "gross_revenue": 5372.37,
    "total_refunds": 772.14,
    "total_shipping": 126.08,
    "total_platform_fees": 107.48,
    "total_promo_credits": 132.01,
    "commissionable_base": 4234.66,
    "commission_rate": 0.08,
    "gross_commission": 338.77,
    "net_payout_native": 338.77,
    "net_payout_usd": 338.77,
    "meets_minimum_threshold": true,
    "payout_status": "paid_out"
  },
  {
    "creator_id": "c-040",
    "handle": "@bakeryorderform",
    "tier": "plus",
    "currency": "USD",
    "orders_counted": 18,
    "orders_excluded": 3,
    "gross_revenue": 4767.93,
    "total_refunds": 262.67,
    "total_shipping": 125.52,
    "total_platform_fees": 95.35,
    "total_promo_credits": 67.65,
    "commissionable_base": 4216.74,
    "commission_rate": 0.11,
    "gross_commission": 463.84,
    "net_payout_native": 463.84,
    "net_payout_usd": 463.84,
    "meets_minimum_threshold": true,
    "payout_status": "paid_out"
  },
  {
    "creator_id": "c-041",
    "handle": "@trailheadsundries",
    "tier": "standard",
    "currency": "USD",
    "orders_counted": 11,
    "orders_excluded": 0,
    "gross_revenue": 2185.09,
    "total_refunds": 195.37,
    "total_shipping": 74.01,
    "total_platform_fees": 43.72,
    "total_promo_credits": 23.24,
    "commissionable_base": 1848.75,
    "commission_rate": 0.08,
    "gross_commission": 147.9,
    "net_payout_native": 147.9,
    "net_payout_usd": 147.9,
    "meets_minimum_threshold": true,
    "payout_status": "paid_out"
  },
  {
    "creator_id": "c-042",
    "handle": "@thirdsundayhome",
    "tier": "plus",
    "currency": "EUR",
    "orders_counted": 23,
    "orders_excluded": 3,
    "gross_revenue": 4642.21,
    "total_refunds": 0,
    "total_shipping": 133.52,
    "total_platform_fees": 92.85,
    "total_promo_credits": 99.59,
    "commissionable_base": 4316.25,
    "commission_rate": 0.11,
    "gross_commission": 474.79,
    "net_payout_native": 474.79,
    "net_payout_usd": 517.52,
    "meets_minimum_threshold": true,
    "payout_status": "paid_out"
  },
  {
    "creator_id": "c-043",
    "handle": "@swatchscience",
    "tier": "elite",
    "currency": "USD",
    "orders_counted": 23,
    "orders_excluded": 5,
    "gross_revenue": 4701.28,
    "total_refunds": 92.39,
    "total_shipping": 128.92,
    "total_platform_fees": 94.03,
    "total_promo_credits": 51.13,
    "commissionable_base": 4385.94,
    "commission_rate": 0.14,
    "gross_commission": 614.03,
    "net_payout_native": 614.03,
    "net_payout_usd": 614.03,
    "meets_minimum_threshold": true,
    "payout_status": "paid_out"
  },
  {
    "creator_id": "c-044",
    "handle": "@modestmodern.fit",
    "tier": "standard",
    "currency": "USD",
    "orders_counted": 8,
    "orders_excluded": 1,
    "gross_revenue": 994.73,
    "total_refunds": 0,
    "total_shipping": 53.49,
    "total_platform_fees": 19.9,
    "total_promo_credits": 43.99,
    "commissionable_base": 877.35,
    "commission_rate": 0.08,
    "gross_commission": 70.19,
    "net_payout_native": 70.19,
    "net_payout_usd": 70.19,
    "meets_minimum_threshold": true,
    "payout_status": "paid_out"
  },
  {
    "creator_id": "c-045",
    "handle": "@runonsentence.tech",
    "tier": "plus",
    "currency": "USD",
    "orders_counted": 14,
    "orders_excluded": 1,
    "gross_revenue": 2816.28,
    "total_refunds": 0,
    "total_shipping": 91.36,
    "total_platform_fees": 56.32,
    "total_promo_credits": 73.36,
    "commissionable_base": 2595.24,
    "commission_rate": 0.11,
    "gross_commission": 285.48,
    "net_payout_native": 285.48,
    "net_payout_usd": 285.48,
    "meets_minimum_threshold": true,
    "payout_status": "paid_out"
  },
  {
    "creator_id": "c-046",
    "handle": "@palettework",
    "tier": "standard",
    "currency": "USD",
    "orders_counted": 17,
    "orders_excluded": 0,
    "gross_revenue": 4135.43,
    "total_refunds": 0,
    "total_shipping": 107.16,
    "total_platform_fees": 82.7,
    "total_promo_credits": 128.92,
    "commissionable_base": 3816.65,
    "commission_rate": 0.08,
    "gross_commission": 305.33,
    "net_payout_native": 305.33,
    "net_payout_usd": 305.33,
    "meets_minimum_threshold": true,
    "payout_status": "paid_out"
  },
  {
    "creator_id": "c-047",
    "handle": "@hourstack",
    "tier": "plus",
    "currency": "GBP",
    "orders_counted": 10,
    "orders_excluded": 0,
    "gross_revenue": 1982.54,
    "total_refunds": 287.63,
    "total_shipping": 68.14,
    "total_platform_fees": 39.66,
    "total_promo_credits": 96.31,
    "commissionable_base": 1490.8,
    "commission_rate": 0.11,
    "gross_commission": 163.99,
    "net_payout_native": 163.99,
    "net_payout_usd": 209.9,
    "meets_minimum_threshold": true,
    "payout_status": "paid_out"
  },
  {
    "creator_id": "c-048",
    "handle": "@evenkettle",
    "tier": "standard",
    "currency": "USD",
    "orders_counted": 15,
    "orders_excluded": 1,
    "gross_revenue": 3321.49,
    "total_refunds": 0,
    "total_shipping": 75.65,
    "total_platform_fees": 66.44,
    "total_promo_credits": 69.34,
    "commissionable_base": 3110.06,
    "commission_rate": 0.08,
    "gross_commission": 248.8,
    "net_payout_native": 248.8,
    "net_payout_usd": 248.8,
    "meets_minimum_threshold": true,
    "payout_status": "paid_out"
  },
  {
    "creator_id": "c-049",
    "handle": "@porchtide",
    "tier": "plus",
    "currency": "USD",
    "orders_counted": 21,
    "orders_excluded": 1,
    "gross_revenue": 4487.49,
    "total_refunds": 100.92,
    "total_shipping": 133.35,
    "total_platform_fees": 89.75,
    "total_promo_credits": 108.41,
    "commissionable_base": 4055.06,
    "commission_rate": 0.11,
    "gross_commission": 446.06,
    "net_payout_native": 446.06,
    "net_payout_usd": 446.06,
    "meets_minimum_threshold": true,
    "payout_status": "paid_out"
  },
  {
    "creator_id": "c-050",
    "handle": "@goldhourgrocer",
    "tier": "elite",
    "currency": "USD",
    "orders_counted": 9,
    "orders_excluded": 1,
    "gross_revenue": 1922.63,
    "total_refunds": 239.39,
    "total_shipping": 47.11,
    "total_platform_fees": 38.47,
    "total_promo_credits": 0,
    "commissionable_base": 1597.66,
    "commission_rate": 0.14,
    "gross_commission": 223.67,
    "net_payout_native": 223.67,
    "net_payout_usd": 223.67,
    "meets_minimum_threshold": true,
    "payout_status": "paid_out"
  }
]